<?xml version="1.0" encoding="UTF-8"?>
<objects serializationModel="Studio.02.02.00">
	<object class="AudioFile" id="{7d1e7df9-be38-4df2-a9b5-2d84cf5067c3}">
		<property name="assetPath">
			<value>PC_HIT_SLASH_05.wav</value>
		</property>
		<property name="frequencyInKHz">
			<value>48</value>
		</property>
		<property name="channelCount">
			<value>2</value>
		</property>
		<property name="length">
			<value>0.33512500000000001</value>
		</property>
		<relationship name="masterAssetFolder">
			<destination>{0ea6db39-10d9-46be-b01c-92aec614a6ba}</destination>
		</relationship>
	</object>
</objects>
